keepass_ssh/__init__.py
keepass_ssh/cli.py
keepass_ssh/database.py
keepass_ssh/main.py
keepass_ssh/pyproject.toml
keepass_ssh/server.py
keepass_ssh/ssh.py
keepass_ssh_connect-0.1.0.dist-info/entry_points.txt
keepass_ssh_connect-0.1.0.dist-info/LICENSE
keepass_ssh_connect-0.1.0.dist-info/METADATA
keepass_ssh_connect-0.1.0.dist-info/WHEEL
keepass_ssh_connect-0.1.0.dist-info/RECORD
