Metadata-Version: 2.3
Name: keepass-ssh-connect
Version: 0.1.0
Summary: A Python utility that helps you securely connect to SSH servers using credentials stored in a KeePass database
License: MIT
Keywords: keepass,ssh,connection,security
Author: Grzes-94
Requires-Python: >=3.8
Classifier: Development Status :: 3 - Alpha
Classifier: Intended Audience :: System Administrators
Classifier: License :: OSI Approved :: MIT License
Classifier: Programming Language :: Python :: 3
Classifier: Programming Language :: Python :: 3.8
Classifier: Programming Language :: Python :: 3.9
Classifier: Programming Language :: Python :: 3.10
Classifier: Programming Language :: Python :: 3.11
Classifier: Programming Language :: Python :: 3.12
Classifier: Programming Language :: Python :: 3.13
Classifier: Topic :: Security
Classifier: Topic :: System :: Networking
Requires-Dist: colorama (>=0.4.6,<0.5.0)
Requires-Dist: paramiko (>=3.0.0,<4.0.0)
Requires-Dist: pykeepass (>=4.1.0,<5.0.0)
Requires-Dist: python-dotenv (>=1.0.0,<2.0.0)
Project-URL: Bug Tracker, https://github.com/grzes-94/keepass-ssh-connect/issues
Project-URL: Repository, https://github.com/grzes-94/keepass-ssh-connect
